pyCallBy/__init__.py
pyCallBy-1.2.1.dist-info/LICENSE.md
pyCallBy-1.2.1.dist-info/METADATA
pyCallBy-1.2.1.dist-info/WHEEL
pyCallBy-1.2.1.dist-info/top_level.txt
pyCallBy-1.2.1.dist-info/RECORD
