Metadata-Version: 2.1
Name: pyCallBy
Version: 1.2.1
Summary: Auxilary classes to implement call by reference.
Home-page: https://github.com/Paebbels/pyCallBy
Author: Patrick Lehmann
Author-email: Paebbels@gmail.com
License: UNKNOWN
Project-URL: Documentation, https://pyCallBy.readthedocs.io/en/latest/
Project-URL: Source Code, https://github.com/Paebbels/pyCallBy
Project-URL: Issue Tracker, https://github.com/Paebbels/pyCallBy/issues
Keywords: Python3 Path Generic-Library
Platform: UNKNOWN
Classifier: License :: OSI Approved :: Apache Software License
Classifier: Operating System :: OS Independent
Classifier: Programming Language :: Python :: 3 :: Only
Classifier: Programming Language :: Python :: 3.6
Classifier: Programming Language :: Python :: 3.7
Classifier: Programming Language :: Python :: 3.8
Classifier: Programming Language :: Python :: 3.9
Classifier: Development Status :: 5 - Production/Stable
Classifier: Intended Audience :: Developers
Classifier: Topic :: Utilities
Requires-Python: >=3.6
Requires-Dist: pydecor (>=2.0.1)
